.gitignore
.pre-commit-config.yaml
LICENSE
README.md
mkdocs.yml
pyproject.toml
requirements.txt
setup.cfg
setup.py
.github/FUNDING.yml
Knexpy/__init__.py
Knexpy/builder.py
Knexpy/core.py
Knexpy/utils.py
docs/index.md
docs/Query Builder/Knex.md
docs/Query Builder/count.md
docs/Query Builder/delete.md
docs/Query Builder/execute.md
docs/Query Builder/from.md
docs/Query Builder/insert.md
docs/Query Builder/insert_json.md
docs/Query Builder/insert_many.md
docs/Query Builder/limit.md
docs/Query Builder/order_by.md
docs/Query Builder/query.md
docs/Query Builder/raw.md
docs/Query Builder/select.md
docs/Query Builder/subquery.md
docs/Query Builder/table.md
docs/Query Builder/update.md
docs/Query Builder/where.md
docs/Query Builder/where_in.md
docs/Query Builder/where_not_null.md
docs/Query Builder/where_null.md
docs/Transactions/begin.md
docs/Transactions/commit.md
docs/Transactions/rollback.md
docs/Utilities/to_string.md
docs/fields/Fields.md
docs/fields/blob.md
docs/fields/boolean.md
docs/fields/date.md
docs/fields/datetime.md
docs/fields/double.md
docs/fields/float.md
docs/fields/foreign_key.md
docs/fields/integer.md
docs/fields/text.md
docs/fields/varchar.md
docs/roadmap/roadmap.md
examples/README.md
examples/example 1.py
examples/example 2.py
examples/example 3.py
examples/seed.py
knexpy.egg-info/PKG-INFO
knexpy.egg-info/SOURCES.txt
knexpy.egg-info/dependency_links.txt
knexpy.egg-info/requires.txt
knexpy.egg-info/top_level.txt
static/Demo.gif