Metadata-Version: 2.1
Name: knexpy
Version: 0.1.3
Summary: A KnexJS like module for abstracting Python's SQLite
Home-page: https://github.com/carlossilva2/Knexpy
Author: Carlos Silva
Author-email: carlos.miguel.silva@protonmail.com
License: GPLv3
Project-URL: Source, https://github.com/carlossilva2/Knexpy
Project-URL: Documentation, https://knexpy.readthedocs.io
Platform: UNKNOWN
Classifier: Development Status :: 4 - Beta
Classifier: Environment :: Console
Classifier: Intended Audience :: Developers
Classifier: License :: OSI Approved :: GNU General Public License v3 (GPLv3)
Classifier: Natural Language :: English
Classifier: Operating System :: OS Independent
Classifier: Programming Language :: Python :: 3
Classifier: Programming Language :: Python :: 3.9
Classifier: Programming Language :: Python :: 3.10
Classifier: Topic :: Software Development
Classifier: Typing :: Typed
Requires-Python: >=3.9
License-File: LICENSE
